<?xml version="1.0" encoding="UTF-8" standalone="no"?>
<?OntoDPSData docID="18340" markupID="3051" OntoTechnologyVersion="2.6.1.79"?>
<rdf:RDF xmlns:rdf="http://www.w3.org/1999/02/22-rdf-syntax-ns#" xmlns:Aux="http://www.abbyy.com/ns/Aux#" xmlns:Basic="http://www.abbyy.com/ns/Basic#" xmlns:rdfs="http://www.w3.org/2000/01/rdf-schema#" xmlns:BasicEntity="http://www.abbyy.com/ns/BasicEntity#" xmlns:Org="http://www.abbyy.com/ns/Org#" xmlns:Geo="http://www.abbyy.com/ns/Geo#">
	<Geo:Country rdf:about="http://www.abbyy.com/ns/Geo#Russia">
		<Basic:identifier xml:lang="ru-RU">Россия</Basic:identifier>
		<Basic:key_word xml:lang="ru-RU">страна</Basic:key_word>
	</Geo:Country>
	<BasicEntity:Person rdf:nodeID="bnode60A62D8C-CD51-40A4-A06F-B65DDAEE0CBE">
		<rdfs:label xml:lang="ru-RU">Ксавье Ришо</rdfs:label>
		<BasicEntity:firstname xml:lang="ru-RU">Ксавье</BasicEntity:firstname>
		<BasicEntity:surname xml:lang="ru-RU">Ришо</BasicEntity:surname>
		<Basic:named rdf:datatype="http://www.w3.org/2001/XMLSchema#boolean">true</Basic:named>
	</BasicEntity:Person>
	<Geo:Country rdf:about="http://www.abbyy.com/ns/Geo#France">
		<Basic:identifier xml:lang="ru-RU">Франция</Basic:identifier>
		<Basic:key_word xml:lang="ru-RU">страна</Basic:key_word>
	</Geo:Country>
	<BasicEntity:Money rdf:nodeID="bnode2892CF47-C2CE-4A14-BBAD-93BF225DC0C5">
		<rdfs:label xml:lang="ru-RU">до 150 тысяч евро</rdfs:label>
		<BasicEntity:measure_name xml:lang="ru-RU">евро</BasicEntity:measure_name>
		<Basic:value rdf:datatype="http://www.w3.org/2001/XMLSchema#integer">150000</Basic:value>
	</BasicEntity:Money>
	<BasicEntity:Person rdf:nodeID="bnode43485453-EFD4-4190-B030-7617C46964F1">
		<rdfs:label xml:lang="ru-RU">Xavier Richaud</rdfs:label>
		<BasicEntity:firstname xml:lang="ru-RU">Xavier</BasicEntity:firstname>
		<BasicEntity:surname xml:lang="ru-RU">Richaud</BasicEntity:surname>
		<Basic:named rdf:datatype="http://www.w3.org/2001/XMLSchema#boolean">true</Basic:named>
	</BasicEntity:Person>
	<Geo:InhabitedLocality rdf:nodeID="bnode78DEF571-4840-4931-8730-71E7C16D0EE8">
		<Basic:identifier xml:lang="ru-RU">Куршевель</Basic:identifier>
		<rdfs:label xml:lang="ru-RU">Куршевель</rdfs:label>
	</Geo:InhabitedLocality>
	<Geo:InhabitedLocality rdf:nodeID="bnode26382FBA-0D2B-4227-B20D-5B1CB0975D19">
		<Basic:identifier xml:lang="ru-RU">Лион</Basic:identifier>
		<rdfs:label xml:lang="ru-RU">город Лион</rdfs:label>
		<Basic:key_word xml:lang="ru-RU">город</Basic:key_word>
	</Geo:InhabitedLocality>
	<Org:Commercial rdf:nodeID="bnodeAB10DAFC-1914-4C72-BE0A-3DD72880E365">
		<Basic:identifier xml:lang="ru-RU">Норильский никель</Basic:identifier>
		<rdfs:label xml:lang="ru-RU">"Норильский никель"</rdfs:label>
		<Basic:named rdf:datatype="http://www.w3.org/2001/XMLSchema#boolean">true</Basic:named>
	</Org:Commercial>
	<BasicEntity:Person rdf:nodeID="bnode929C2524-A520-4F28-9E61-F24FD2631DAE">
		<rdfs:label xml:lang="ru-RU">Михаил Прохоров</rdfs:label>
		<BasicEntity:firstname xml:lang="ru-RU">Михаил</BasicEntity:firstname>
		<BasicEntity:surname xml:lang="ru-RU">Прохоров</BasicEntity:surname>
		<Basic:named rdf:datatype="http://www.w3.org/2001/XMLSchema#boolean">true</Basic:named>
	</BasicEntity:Person>
	<Aux:TextAnnotations rdf:nodeID="bnodeA0A74783-F232-46C3-9083-EEDBB4B1085D">
		<Aux:document_text xml:lang="ru-RU">&lt;title&gt;Ришо, Ксавье&lt;/title&gt; &lt;annotation&gt;Прокурор Лиона&lt;/annotation&gt; &lt;description&gt;Прокурор города Лион. В январе 2007 года имя Ришо упоминалось в прессе в связи со скандалом вокруг ареста во Франции российского предпринимателя Михаила Прохорова.&lt;/description&gt; &lt;body&gt;  Ксавье Ришо (Xavier Richaud) – прокурор французского города Лион, получивший известность после ареста во Франции российского миллиардера, в то время главы компании "Норильский никель" Михаила Прохорова. Прохоров был арестован в горнолыжном курорте Куршевель 9 января 2007 года. 11 января Ришо рассказал журналистам об аресте олигарха: по словам прокурора, вместе с Прохоровым были задержаны двое его помощников, двое представителей "Норильского никеля" и десять женщин. Ришо сообщил, что арест Прохорова стал результатом длительного расследования. По данным СМИ, оно началось в 2006 году, когда стало известно, что многочисленные женщины из России доставлялись в Куршевель, где предположительно занимались проституцией. Прохоров же на организованных им вечеринках якобы предлагал услуги проституток своим гостям. В случае выдвижения против Прохорова официальных обвинений он должен был бы 12 января предстать перед судом, и ему грозил бы срок тюремного заключения до семи лет и штраф в размере до 150 тысяч евро – такое наказание предусмотрено французским законодательством за сутенерство. Однако до суда дело не дошло: после допроса у следователей российский олигарх и другие задержанные были освобождены. Ришо сообщил, что на допросе Прохоров отрицал свою причастность к работе сутенерской сети. Прокурор подчеркнул, что, хотя прямых улик против Прохорова найдено не было, в будущем не исключен повторный вызов россиянина на допрос. После освобождения Прохоров вернулся в Россию. &lt;/body&gt;</Aux:document_text>
		<Aux:annotation>
			<Aux:InstanceAnnotation rdf:nodeID="bnode1ABD8969-4AFA-4909-A34D-AD1D5EC26552">
				<Aux:annotation_start rdf:datatype="http://www.w3.org/2001/XMLSchema#integer">7</Aux:annotation_start>
				<Aux:annotation_end rdf:datatype="http://www.w3.org/2001/XMLSchema#integer">11</Aux:annotation_end>
				<Aux:instance rdf:nodeID="bnode60A62D8C-CD51-40A4-A06F-B65DDAEE0CBE"/>
			</Aux:InstanceAnnotation>
		</Aux:annotation>
		<Aux:annotation>
			<Aux:InstanceAnnotation rdf:nodeID="bnode0FF8A7E9-0FB0-47D1-9CAF-626B3C5C406A">
				<Aux:annotation_start rdf:datatype="http://www.w3.org/2001/XMLSchema#integer">13</Aux:annotation_start>
				<Aux:annotation_end rdf:datatype="http://www.w3.org/2001/XMLSchema#integer">19</Aux:annotation_end>
				<Aux:instance rdf:nodeID="bnode60A62D8C-CD51-40A4-A06F-B65DDAEE0CBE"/>
			</Aux:InstanceAnnotation>
		</Aux:annotation>
		<Aux:annotation>
			<Aux:InstanceAnnotation rdf:nodeID="bnodeAB0DBE5D-D186-4D3A-9501-6C3FDB91F6F5">
				<Aux:annotation_start rdf:datatype="http://www.w3.org/2001/XMLSchema#integer">40</Aux:annotation_start>
				<Aux:annotation_end rdf:datatype="http://www.w3.org/2001/XMLSchema#integer">48</Aux:annotation_end>
				<Aux:instance rdf:nodeID="bnode60A62D8C-CD51-40A4-A06F-B65DDAEE0CBE"/>
			</Aux:InstanceAnnotation>
		</Aux:annotation>
		<Aux:annotation>
			<Aux:InstanceAnnotation rdf:nodeID="bnodeDB195C4F-7948-4DAD-9D19-12C8E77946D7">
				<Aux:annotation_start rdf:datatype="http://www.w3.org/2001/XMLSchema#integer">49</Aux:annotation_start>
				<Aux:annotation_end rdf:datatype="http://www.w3.org/2001/XMLSchema#integer">54</Aux:annotation_end>
				<Aux:instance rdf:nodeID="bnode26382FBA-0D2B-4227-B20D-5B1CB0975D19"/>
			</Aux:InstanceAnnotation>
		</Aux:annotation>
		<Aux:annotation>
			<Aux:InstanceAnnotation rdf:nodeID="bnodeAB76AE81-BB2C-43F0-9FD1-61E945D72D2A">
				<Aux:annotation_start rdf:datatype="http://www.w3.org/2001/XMLSchema#integer">81</Aux:annotation_start>
				<Aux:annotation_end rdf:datatype="http://www.w3.org/2001/XMLSchema#integer">89</Aux:annotation_end>
				<Aux:instance rdf:nodeID="bnode60A62D8C-CD51-40A4-A06F-B65DDAEE0CBE"/>
			</Aux:InstanceAnnotation>
		</Aux:annotation>
		<Aux:annotation>
			<Aux:InstanceAnnotation rdf:nodeID="bnodeC1FE2EBD-B32C-4B24-89EC-5319A324791C">
				<Aux:annotation_start rdf:datatype="http://www.w3.org/2001/XMLSchema#integer">90</Aux:annotation_start>
				<Aux:annotation_end rdf:datatype="http://www.w3.org/2001/XMLSchema#integer">101</Aux:annotation_end>
				<Aux:instance rdf:nodeID="bnode26382FBA-0D2B-4227-B20D-5B1CB0975D19"/>
			</Aux:InstanceAnnotation>
		</Aux:annotation>
		<Aux:annotation>
			<Aux:InstanceAnnotation rdf:nodeID="bnode6F834727-5B2E-44DC-AA13-501D6DE1C411">
				<Aux:annotation_start rdf:datatype="http://www.w3.org/2001/XMLSchema#integer">126</Aux:annotation_start>
				<Aux:annotation_end rdf:datatype="http://www.w3.org/2001/XMLSchema#integer">130</Aux:annotation_end>
				<Aux:instance rdf:nodeID="bnode60A62D8C-CD51-40A4-A06F-B65DDAEE0CBE"/>
			</Aux:InstanceAnnotation>
		</Aux:annotation>
		<Aux:annotation>
			<Aux:InstanceAnnotation rdf:nodeID="bnodeBFE93010-28DE-4B69-8D04-24138F9CD2EC">
				<Aux:annotation_start rdf:datatype="http://www.w3.org/2001/XMLSchema#integer">190</Aux:annotation_start>
				<Aux:annotation_end rdf:datatype="http://www.w3.org/2001/XMLSchema#integer">197</Aux:annotation_end>
				<Aux:instance rdf:resource="http://www.abbyy.com/ns/Geo#France"/>
			</Aux:InstanceAnnotation>
		</Aux:annotation>
		<Aux:annotation>
			<Aux:InstanceAnnotation rdf:nodeID="bnode33C793CB-150E-49F9-AAFA-494AFCE4D8BC">
				<Aux:annotation_start rdf:datatype="http://www.w3.org/2001/XMLSchema#integer">198</Aux:annotation_start>
				<Aux:annotation_end rdf:datatype="http://www.w3.org/2001/XMLSchema#integer">209</Aux:annotation_end>
				<Aux:instance rdf:resource="http://www.abbyy.com/ns/Geo#Russia"/>
			</Aux:InstanceAnnotation>
		</Aux:annotation>
		<Aux:annotation>
			<Aux:InstanceAnnotation rdf:nodeID="bnode8BC2907A-4321-47B6-B963-DF538B26947C">
				<Aux:annotation_start rdf:datatype="http://www.w3.org/2001/XMLSchema#integer">226</Aux:annotation_start>
				<Aux:annotation_end rdf:datatype="http://www.w3.org/2001/XMLSchema#integer">243</Aux:annotation_end>
				<Aux:instance rdf:nodeID="bnode929C2524-A520-4F28-9E61-F24FD2631DAE"/>
			</Aux:InstanceAnnotation>
		</Aux:annotation>
		<Aux:annotation>
			<Aux:InstanceAnnotation rdf:nodeID="bnode767DC261-872E-4B85-B2AA-921B117C4805">
				<Aux:annotation_start rdf:datatype="http://www.w3.org/2001/XMLSchema#integer">267</Aux:annotation_start>
				<Aux:annotation_end rdf:datatype="http://www.w3.org/2001/XMLSchema#integer">278</Aux:annotation_end>
				<Aux:instance rdf:nodeID="bnode60A62D8C-CD51-40A4-A06F-B65DDAEE0CBE"/>
			</Aux:InstanceAnnotation>
		</Aux:annotation>
		<Aux:annotation>
			<Aux:InstanceAnnotation rdf:nodeID="bnode358CE4F6-5214-4B8A-9036-71820E0AD5B5">
				<Aux:annotation_start rdf:datatype="http://www.w3.org/2001/XMLSchema#integer">280</Aux:annotation_start>
				<Aux:annotation_end rdf:datatype="http://www.w3.org/2001/XMLSchema#integer">294</Aux:annotation_end>
				<Aux:instance rdf:nodeID="bnode43485453-EFD4-4190-B030-7617C46964F1"/>
			</Aux:InstanceAnnotation>
		</Aux:annotation>
		<Aux:annotation>
			<Aux:InstanceAnnotation rdf:nodeID="bnodeCFB28C63-298A-47DF-90E0-C2F9311F88CF">
				<Aux:annotation_start rdf:datatype="http://www.w3.org/2001/XMLSchema#integer">307</Aux:annotation_start>
				<Aux:annotation_end rdf:datatype="http://www.w3.org/2001/XMLSchema#integer">319</Aux:annotation_end>
				<Aux:instance rdf:resource="http://www.abbyy.com/ns/Geo#France"/>
			</Aux:InstanceAnnotation>
		</Aux:annotation>
		<Aux:annotation>
			<Aux:InstanceAnnotation rdf:nodeID="bnode536EC16A-C9CF-415B-9C71-7CE93CFDFE8C">
				<Aux:annotation_start rdf:datatype="http://www.w3.org/2001/XMLSchema#integer">320</Aux:annotation_start>
				<Aux:annotation_end rdf:datatype="http://www.w3.org/2001/XMLSchema#integer">331</Aux:annotation_end>
				<Aux:instance rdf:nodeID="bnode26382FBA-0D2B-4227-B20D-5B1CB0975D19"/>
			</Aux:InstanceAnnotation>
		</Aux:annotation>
		<Aux:annotation>
			<Aux:InstanceAnnotation rdf:nodeID="bnode1A2EEA77-BF65-4BAF-81D6-662EFAA3844B">
				<Aux:annotation_start rdf:datatype="http://www.w3.org/2001/XMLSchema#integer">372</Aux:annotation_start>
				<Aux:annotation_end rdf:datatype="http://www.w3.org/2001/XMLSchema#integer">379</Aux:annotation_end>
				<Aux:instance rdf:resource="http://www.abbyy.com/ns/Geo#France"/>
			</Aux:InstanceAnnotation>
		</Aux:annotation>
		<Aux:annotation>
			<Aux:InstanceAnnotation rdf:nodeID="bnode85046844-8092-497B-B318-B6E9A6466C28">
				<Aux:annotation_start rdf:datatype="http://www.w3.org/2001/XMLSchema#integer">380</Aux:annotation_start>
				<Aux:annotation_end rdf:datatype="http://www.w3.org/2001/XMLSchema#integer">391</Aux:annotation_end>
				<Aux:instance rdf:resource="http://www.abbyy.com/ns/Geo#Russia"/>
			</Aux:InstanceAnnotation>
		</Aux:annotation>
		<Aux:annotation>
			<Aux:InstanceAnnotation rdf:nodeID="bnode83B597D7-DAF7-4E81-BEAF-B075F033B955">
				<Aux:annotation_start rdf:datatype="http://www.w3.org/2001/XMLSchema#integer">422</Aux:annotation_start>
				<Aux:annotation_end rdf:datatype="http://www.w3.org/2001/XMLSchema#integer">450</Aux:annotation_end>
				<Aux:instance rdf:nodeID="bnodeAB10DAFC-1914-4C72-BE0A-3DD72880E365"/>
			</Aux:InstanceAnnotation>
		</Aux:annotation>
		<Aux:annotation>
			<Aux:InstanceAnnotation rdf:nodeID="bnode7B887D44-8206-41AC-B973-E0F02598044C">
				<Aux:annotation_start rdf:datatype="http://www.w3.org/2001/XMLSchema#integer">451</Aux:annotation_start>
				<Aux:annotation_end rdf:datatype="http://www.w3.org/2001/XMLSchema#integer">468</Aux:annotation_end>
				<Aux:instance rdf:nodeID="bnode929C2524-A520-4F28-9E61-F24FD2631DAE"/>
			</Aux:InstanceAnnotation>
		</Aux:annotation>
		<Aux:annotation>
			<Aux:InstanceAnnotation rdf:nodeID="bnode7BD198B4-873A-4D9D-AFB6-A9CA5BC46B6C">
				<Aux:annotation_start rdf:datatype="http://www.w3.org/2001/XMLSchema#integer">470</Aux:annotation_start>
				<Aux:annotation_end rdf:datatype="http://www.w3.org/2001/XMLSchema#integer">478</Aux:annotation_end>
				<Aux:instance rdf:nodeID="bnode929C2524-A520-4F28-9E61-F24FD2631DAE"/>
			</Aux:InstanceAnnotation>
		</Aux:annotation>
		<Aux:annotation>
			<Aux:InstanceAnnotation rdf:nodeID="bnode1E356E88-6D34-4451-A32E-ABB29A9C32A7">
				<Aux:annotation_start rdf:datatype="http://www.w3.org/2001/XMLSchema#integer">515</Aux:annotation_start>
				<Aux:annotation_end rdf:datatype="http://www.w3.org/2001/XMLSchema#integer">524</Aux:annotation_end>
				<Aux:instance rdf:nodeID="bnode78DEF571-4840-4931-8730-71E7C16D0EE8"/>
			</Aux:InstanceAnnotation>
		</Aux:annotation>
		<Aux:annotation>
			<Aux:InstanceAnnotation rdf:nodeID="bnode095CD6BD-70EE-4D4C-B9CD-CC3AF36C815E">
				<Aux:annotation_start rdf:datatype="http://www.w3.org/2001/XMLSchema#integer">555</Aux:annotation_start>
				<Aux:annotation_end rdf:datatype="http://www.w3.org/2001/XMLSchema#integer">559</Aux:annotation_end>
				<Aux:instance rdf:nodeID="bnode60A62D8C-CD51-40A4-A06F-B65DDAEE0CBE"/>
			</Aux:InstanceAnnotation>
		</Aux:annotation>
		<Aux:annotation>
			<Aux:InstanceAnnotation rdf:nodeID="bnode85EDCD3C-A8CC-4673-A198-4CE2F8B7D4B7">
				<Aux:annotation_start rdf:datatype="http://www.w3.org/2001/XMLSchema#integer">592</Aux:annotation_start>
				<Aux:annotation_end rdf:datatype="http://www.w3.org/2001/XMLSchema#integer">600</Aux:annotation_end>
				<Aux:instance rdf:nodeID="bnode929C2524-A520-4F28-9E61-F24FD2631DAE"/>
			</Aux:InstanceAnnotation>
		</Aux:annotation>
		<Aux:annotation>
			<Aux:InstanceAnnotation rdf:nodeID="bnode4E835602-B465-46C9-91BB-F501083141AD">
				<Aux:annotation_start rdf:datatype="http://www.w3.org/2001/XMLSchema#integer">612</Aux:annotation_start>
				<Aux:annotation_end rdf:datatype="http://www.w3.org/2001/XMLSchema#integer">621</Aux:annotation_end>
				<Aux:instance rdf:nodeID="bnode60A62D8C-CD51-40A4-A06F-B65DDAEE0CBE"/>
			</Aux:InstanceAnnotation>
		</Aux:annotation>
		<Aux:annotation>
			<Aux:InstanceAnnotation rdf:nodeID="bnodeC5D102D8-299A-4412-BFA7-A44011954AEB">
				<Aux:annotation_start rdf:datatype="http://www.w3.org/2001/XMLSchema#integer">632</Aux:annotation_start>
				<Aux:annotation_end rdf:datatype="http://www.w3.org/2001/XMLSchema#integer">642</Aux:annotation_end>
				<Aux:instance rdf:nodeID="bnode929C2524-A520-4F28-9E61-F24FD2631DAE"/>
			</Aux:InstanceAnnotation>
		</Aux:annotation>
		<Aux:annotation>
			<Aux:InstanceAnnotation rdf:nodeID="bnode77758776-2E73-4689-8DA2-98FF13CD946F">
				<Aux:annotation_start rdf:datatype="http://www.w3.org/2001/XMLSchema#integer">663</Aux:annotation_start>
				<Aux:annotation_end rdf:datatype="http://www.w3.org/2001/XMLSchema#integer">666</Aux:annotation_end>
				<Aux:instance rdf:nodeID="bnode929C2524-A520-4F28-9E61-F24FD2631DAE"/>
			</Aux:InstanceAnnotation>
		</Aux:annotation>
		<Aux:annotation>
			<Aux:InstanceAnnotation rdf:nodeID="bnode97F3C76E-C847-4780-991E-7C2EBD8DBA03">
				<Aux:annotation_start rdf:datatype="http://www.w3.org/2001/XMLSchema#integer">699</Aux:annotation_start>
				<Aux:annotation_end rdf:datatype="http://www.w3.org/2001/XMLSchema#integer">719</Aux:annotation_end>
				<Aux:instance rdf:nodeID="bnodeAB10DAFC-1914-4C72-BE0A-3DD72880E365"/>
			</Aux:InstanceAnnotation>
		</Aux:annotation>
		<Aux:annotation>
			<Aux:InstanceAnnotation rdf:nodeID="bnode0008FDFC-A1C0-4D27-BEC6-58D4EAA1EF89">
				<Aux:annotation_start rdf:datatype="http://www.w3.org/2001/XMLSchema#integer">737</Aux:annotation_start>
				<Aux:annotation_end rdf:datatype="http://www.w3.org/2001/XMLSchema#integer">741</Aux:annotation_end>
				<Aux:instance rdf:nodeID="bnode60A62D8C-CD51-40A4-A06F-B65DDAEE0CBE"/>
			</Aux:InstanceAnnotation>
		</Aux:annotation>
		<Aux:annotation>
			<Aux:InstanceAnnotation rdf:nodeID="bnodeBE9135E7-3E18-481A-9FAA-49031FF55C4E">
				<Aux:annotation_start rdf:datatype="http://www.w3.org/2001/XMLSchema#integer">761</Aux:annotation_start>
				<Aux:annotation_end rdf:datatype="http://www.w3.org/2001/XMLSchema#integer">770</Aux:annotation_end>
				<Aux:instance rdf:nodeID="bnode929C2524-A520-4F28-9E61-F24FD2631DAE"/>
			</Aux:InstanceAnnotation>
		</Aux:annotation>
		<Aux:annotation>
			<Aux:InstanceAnnotation rdf:nodeID="bnode646E8E45-4166-4AF9-9E16-34E293FAD96F">
				<Aux:annotation_start rdf:datatype="http://www.w3.org/2001/XMLSchema#integer">908</Aux:annotation_start>
				<Aux:annotation_end rdf:datatype="http://www.w3.org/2001/XMLSchema#integer">914</Aux:annotation_end>
				<Aux:instance rdf:resource="http://www.abbyy.com/ns/Geo#Russia"/>
			</Aux:InstanceAnnotation>
		</Aux:annotation>
		<Aux:annotation>
			<Aux:InstanceAnnotation rdf:nodeID="bnodeE08BE777-F329-41FD-A23F-73F6E2CF1F61">
				<Aux:annotation_start rdf:datatype="http://www.w3.org/2001/XMLSchema#integer">930</Aux:annotation_start>
				<Aux:annotation_end rdf:datatype="http://www.w3.org/2001/XMLSchema#integer">939</Aux:annotation_end>
				<Aux:instance rdf:nodeID="bnode78DEF571-4840-4931-8730-71E7C16D0EE8"/>
			</Aux:InstanceAnnotation>
		</Aux:annotation>
		<Aux:annotation>
			<Aux:InstanceAnnotation rdf:nodeID="bnode41A6F17E-5BBB-4363-99A9-D77562E8176D">
				<Aux:annotation_start rdf:datatype="http://www.w3.org/2001/XMLSchema#integer">987</Aux:annotation_start>
				<Aux:annotation_end rdf:datatype="http://www.w3.org/2001/XMLSchema#integer">995</Aux:annotation_end>
				<Aux:instance rdf:nodeID="bnode929C2524-A520-4F28-9E61-F24FD2631DAE"/>
			</Aux:InstanceAnnotation>
		</Aux:annotation>
		<Aux:annotation>
			<Aux:InstanceAnnotation rdf:nodeID="bnode0CF003F9-3C0F-473C-B431-4E346DC6F266">
				<Aux:annotation_start rdf:datatype="http://www.w3.org/2001/XMLSchema#integer">1017</Aux:annotation_start>
				<Aux:annotation_end rdf:datatype="http://www.w3.org/2001/XMLSchema#integer">1019</Aux:annotation_end>
				<Aux:instance rdf:nodeID="bnode929C2524-A520-4F28-9E61-F24FD2631DAE"/>
			</Aux:InstanceAnnotation>
		</Aux:annotation>
		<Aux:annotation>
			<Aux:InstanceAnnotation rdf:nodeID="bnode2A1D3362-BAA6-41B6-8FFA-0B6D27734762">
				<Aux:annotation_start rdf:datatype="http://www.w3.org/2001/XMLSchema#integer">1066</Aux:annotation_start>
				<Aux:annotation_end rdf:datatype="http://www.w3.org/2001/XMLSchema#integer">1071</Aux:annotation_end>
				<Aux:instance rdf:nodeID="bnode929C2524-A520-4F28-9E61-F24FD2631DAE"/>
			</Aux:InstanceAnnotation>
		</Aux:annotation>
		<Aux:annotation>
			<Aux:InstanceAnnotation rdf:nodeID="bnodeD21268B0-3F09-4128-A642-38AD19262CCA">
				<Aux:annotation_start rdf:datatype="http://www.w3.org/2001/XMLSchema#integer">1107</Aux:annotation_start>
				<Aux:annotation_end rdf:datatype="http://www.w3.org/2001/XMLSchema#integer">1116</Aux:annotation_end>
				<Aux:instance rdf:nodeID="bnode929C2524-A520-4F28-9E61-F24FD2631DAE"/>
			</Aux:InstanceAnnotation>
		</Aux:annotation>
		<Aux:annotation>
			<Aux:InstanceAnnotation rdf:nodeID="bnode7749F924-C8AC-43A4-BD23-2EC1AE27544C">
				<Aux:annotation_start rdf:datatype="http://www.w3.org/2001/XMLSchema#integer">1139</Aux:annotation_start>
				<Aux:annotation_end rdf:datatype="http://www.w3.org/2001/XMLSchema#integer">1141</Aux:annotation_end>
				<Aux:instance rdf:nodeID="bnode929C2524-A520-4F28-9E61-F24FD2631DAE"/>
			</Aux:InstanceAnnotation>
		</Aux:annotation>
		<Aux:annotation>
			<Aux:InstanceAnnotation rdf:nodeID="bnodeE26D5AAD-78C2-45EB-A7D3-D3694271BCB0">
				<Aux:annotation_start rdf:datatype="http://www.w3.org/2001/XMLSchema#integer">1191</Aux:annotation_start>
				<Aux:annotation_end rdf:datatype="http://www.w3.org/2001/XMLSchema#integer">1194</Aux:annotation_end>
				<Aux:instance rdf:nodeID="bnode929C2524-A520-4F28-9E61-F24FD2631DAE"/>
			</Aux:InstanceAnnotation>
		</Aux:annotation>
		<Aux:annotation>
			<Aux:InstanceAnnotation rdf:nodeID="bnodeE255887B-FBC0-4DFF-8A9B-32A13A3DE3B6">
				<Aux:annotation_start rdf:datatype="http://www.w3.org/2001/XMLSchema#integer">1264</Aux:annotation_start>
				<Aux:annotation_end rdf:datatype="http://www.w3.org/2001/XMLSchema#integer">1278</Aux:annotation_end>
				<Aux:instance rdf:nodeID="bnode2892CF47-C2CE-4A14-BBAD-93BF225DC0C5"/>
			</Aux:InstanceAnnotation>
		</Aux:annotation>
		<Aux:annotation>
			<Aux:InstanceAnnotation rdf:nodeID="bnode227048E2-6223-4534-94CA-B9E6BAAAE8AA">
				<Aux:annotation_start rdf:datatype="http://www.w3.org/2001/XMLSchema#integer">1311</Aux:annotation_start>
				<Aux:annotation_end rdf:datatype="http://www.w3.org/2001/XMLSchema#integer">1322</Aux:annotation_end>
				<Aux:instance rdf:resource="http://www.abbyy.com/ns/Geo#France"/>
			</Aux:InstanceAnnotation>
		</Aux:annotation>
		<Aux:annotation>
			<Aux:InstanceAnnotation rdf:nodeID="bnode8D843D05-ADCB-485F-91C0-4CDE98142C4D">
				<Aux:annotation_start rdf:datatype="http://www.w3.org/2001/XMLSchema#integer">1416</Aux:annotation_start>
				<Aux:annotation_end rdf:datatype="http://www.w3.org/2001/XMLSchema#integer">1426</Aux:annotation_end>
				<Aux:instance rdf:resource="http://www.abbyy.com/ns/Geo#Russia"/>
			</Aux:InstanceAnnotation>
		</Aux:annotation>
		<Aux:annotation>
			<Aux:InstanceAnnotation rdf:nodeID="bnode7C2F96CA-AD5C-4CE1-A971-AC6C63D2A6F6">
				<Aux:annotation_start rdf:datatype="http://www.w3.org/2001/XMLSchema#integer">1416</Aux:annotation_start>
				<Aux:annotation_end rdf:datatype="http://www.w3.org/2001/XMLSchema#integer">1434</Aux:annotation_end>
				<Aux:instance rdf:nodeID="bnode929C2524-A520-4F28-9E61-F24FD2631DAE"/>
			</Aux:InstanceAnnotation>
		</Aux:annotation>
		<Aux:annotation>
			<Aux:InstanceAnnotation rdf:nodeID="bnode6710434C-BE9F-4B52-9E01-A4E60E5E9AC7">
				<Aux:annotation_start rdf:datatype="http://www.w3.org/2001/XMLSchema#integer">1474</Aux:annotation_start>
				<Aux:annotation_end rdf:datatype="http://www.w3.org/2001/XMLSchema#integer">1478</Aux:annotation_end>
				<Aux:instance rdf:nodeID="bnode60A62D8C-CD51-40A4-A06F-B65DDAEE0CBE"/>
			</Aux:InstanceAnnotation>
		</Aux:annotation>
		<Aux:annotation>
			<Aux:InstanceAnnotation rdf:nodeID="bnodeA9610D97-08B1-473E-A5A2-DC9BEE1917DC">
				<Aux:annotation_start rdf:datatype="http://www.w3.org/2001/XMLSchema#integer">1503</Aux:annotation_start>
				<Aux:annotation_end rdf:datatype="http://www.w3.org/2001/XMLSchema#integer">1511</Aux:annotation_end>
				<Aux:instance rdf:nodeID="bnode929C2524-A520-4F28-9E61-F24FD2631DAE"/>
			</Aux:InstanceAnnotation>
		</Aux:annotation>
		<Aux:annotation>
			<Aux:InstanceAnnotation rdf:nodeID="bnode815B9EB9-124D-4182-8F91-7F6C722C123E">
				<Aux:annotation_start rdf:datatype="http://www.w3.org/2001/XMLSchema#integer">1565</Aux:annotation_start>
				<Aux:annotation_end rdf:datatype="http://www.w3.org/2001/XMLSchema#integer">1573</Aux:annotation_end>
				<Aux:instance rdf:nodeID="bnode60A62D8C-CD51-40A4-A06F-B65DDAEE0CBE"/>
			</Aux:InstanceAnnotation>
		</Aux:annotation>
		<Aux:annotation>
			<Aux:InstanceAnnotation rdf:nodeID="bnodeCD5EFDE1-D2CF-44E3-B136-9FB650FA8802">
				<Aux:annotation_start rdf:datatype="http://www.w3.org/2001/XMLSchema#integer">1615</Aux:annotation_start>
				<Aux:annotation_end rdf:datatype="http://www.w3.org/2001/XMLSchema#integer">1624</Aux:annotation_end>
				<Aux:instance rdf:nodeID="bnode929C2524-A520-4F28-9E61-F24FD2631DAE"/>
			</Aux:InstanceAnnotation>
		</Aux:annotation>
		<Aux:annotation>
			<Aux:InstanceAnnotation rdf:nodeID="bnodeFF25E091-911F-4CD5-9143-5EEDC0BA71A8">
				<Aux:annotation_start rdf:datatype="http://www.w3.org/2001/XMLSchema#integer">1680</Aux:annotation_start>
				<Aux:annotation_end rdf:datatype="http://www.w3.org/2001/XMLSchema#integer">1690</Aux:annotation_end>
				<Aux:instance rdf:nodeID="bnode929C2524-A520-4F28-9E61-F24FD2631DAE"/>
			</Aux:InstanceAnnotation>
		</Aux:annotation>
		<Aux:annotation>
			<Aux:InstanceAnnotation rdf:nodeID="bnode973F83F3-B2C1-4C3F-BB1E-1A9C09CB9929">
				<Aux:annotation_start rdf:datatype="http://www.w3.org/2001/XMLSchema#integer">1721</Aux:annotation_start>
				<Aux:annotation_end rdf:datatype="http://www.w3.org/2001/XMLSchema#integer">1729</Aux:annotation_end>
				<Aux:instance rdf:nodeID="bnode929C2524-A520-4F28-9E61-F24FD2631DAE"/>
			</Aux:InstanceAnnotation>
		</Aux:annotation>
		<Aux:annotation>
			<Aux:InstanceAnnotation rdf:nodeID="bnodeE2418B57-0052-444B-BA35-99EF72792E0E">
				<Aux:annotation_start rdf:datatype="http://www.w3.org/2001/XMLSchema#integer">1741</Aux:annotation_start>
				<Aux:annotation_end rdf:datatype="http://www.w3.org/2001/XMLSchema#integer">1747</Aux:annotation_end>
				<Aux:instance rdf:resource="http://www.abbyy.com/ns/Geo#Russia"/>
			</Aux:InstanceAnnotation>
		</Aux:annotation>
	</Aux:TextAnnotations>
</rdf:RDF>